hgpack.so
hgpack-1.1.2.dist-info/DESCRIPTION.rst
hgpack-1.1.2.dist-info/METADATA
hgpack-1.1.2.dist-info/RECORD
hgpack-1.1.2.dist-info/WHEEL
hgpack-1.1.2.dist-info/metadata.json
hgpack-1.1.2.dist-info/top_level.txt
