Metadata-Version: 2.0
Name: hgpack
Version: 1.1.2
Summary: HG-means clustering package
Home-page: https://github.com/danielgribel/hg-means
Author: Daniel Gribel
Author-email: dgribel@inf.puc-rio.br
License: UNKNOWN
Keywords: clustering optimization
Platform: UNKNOWN
